etcd3/__init__.py
etcd3/client.py
etcd3/events.py
etcd3/exceptions.py
etcd3/leases.py
etcd3/locks.py
etcd3/members.py
etcd3/transactions.py
etcd3/utils.py
etcd3/watch.py
etcd3/etcdrpc/__init__.py
etcd3/etcdrpc/auth_pb2.py
etcd3/etcdrpc/auth_pb2.pyi
etcd3/etcdrpc/kv_pb2.py
etcd3/etcdrpc/kv_pb2.pyi
etcd3/etcdrpc/rpc_pb2.py
etcd3/etcdrpc/rpc_pb2.pyi
etcd3/etcdrpc/rpc_pb2_grpc.py
python3_etcd3-0.13.0.dist-info/licenses/LICENSE
python3_etcd3-0.13.0.dist-info/METADATA
python3_etcd3-0.13.0.dist-info/WHEEL
python3_etcd3-0.13.0.dist-info/top_level.txt
python3_etcd3-0.13.0.dist-info/RECORD
