Metadata-Version: 2.4
Name: python3-etcd3
Version: 0.13.0
Summary: Python client for etcd v3
Author-email: Louis Taylor <louis@kragniz.eu>
Maintainer-email: VimT <me@vimt.me>
License: Apache-2.0
Project-URL: Homepage, https://github.com/vimt/python3-etcd
Project-URL: Documentation, https://github.com/vimt/python3-etcd
Project-URL: Repository, https://github.com/vimt/python3-etcd
Project-URL: Issues, https://github.com/vimt/python3-etcd/issues
Project-URL: Original Project, https://github.com/kragniz/python-etcd3
Keywords: etcd,etcd3,distributed,key-value,database
Classifier: Development Status :: 4 - Beta
Classifier: Intended Audience :: Developers
Classifier: License :: OSI Approved :: Apache Software License
Classifier: Programming Language :: Python :: 3
Classifier: Programming Language :: Python :: 3.8
Classifier: Programming Language :: Python :: 3.9
Classifier: Programming Language :: Python :: 3.10
Classifier: Programming Language :: Python :: 3.11
Classifier: Programming Language :: Python :: 3.12
Classifier: Topic :: Database
Classifier: Topic :: System :: Distributed Computing
Requires-Python: >=3.8
License-File: LICENSE
Requires-Dist: grpcio>=1.27.0
Requires-Dist: protobuf>=3.6.1
Provides-Extra: dev
Requires-Dist: pytest>=6.0; extra == "dev"
Requires-Dist: pytest-cov; extra == "dev"
Requires-Dist: mypy; extra == "dev"
Requires-Dist: ruff; extra == "dev"
Dynamic: license-file
